bspp/__init__.py
bspp/bspp.py
bspp/hash.py
bspp/model.py
bspp/out_plain_text.py
bspp/postprocess.py
bspp-1.0.1.dist-info/LICENSE
bspp-1.0.1.dist-info/WHEEL
bspp-1.0.1.dist-info/METADATA
bspp-1.0.1.dist-info/RECORD
