Metadata-Version: 2.1
Name: bspp
Version: 1.0.1
Summary: Quake 3 BSP and PK3 map info extractor
Home-page: https://github.com/zsoltm/bspp
License: UNKNOWN
Author: Zsolt Mészárovics
Author-email: zsolt@meszarovics.me
Requires-Python: >=3.7
Classifier: Development Status :: 5 - Production/Stable
Classifier: Intended Audience :: Developers
Classifier: Intended Audience :: End Users/Desktop
Classifier: Topic :: Software Development :: Libraries
Classifier: License :: OSI Approved :: Mozilla Public License 2.0 (MPL 2.0)
Classifier: Programming Language :: Python :: 3
